mcp_server_stdio/__init__.py
mcp_server_stdio/main.py
mcp_server_stdio/core/__init__.py
mcp_server_stdio/core/constants.py
mcp_server_stdio/exceptions/__init__.py
mcp_server_stdio/exceptions/exception_handler.py
mcp_server_stdio/helpers/__init__.py
mcp_server_stdio/helpers/credentials.py
mcp_server_stdio/helpers/http_client.py
mcp_server_stdio/services/__init__.py
mcp_server_stdio/services/compute_offerings_service.py
mcp_server_stdio/tools/__init__.py
mcp_server_stdio/tools/compute_offerings_tool.py
mcp_server_stdio/tools/loader.py
mcp_server_stdio-0.1.10.dist-info/METADATA
mcp_server_stdio-0.1.10.dist-info/WHEEL
mcp_server_stdio-0.1.10.dist-info/entry_points.txt
mcp_server_stdio-0.1.10.dist-info/RECORD
