Metadata-Version: 2.4
Name: mcp-server-stdio
Version: 0.1.10
Summary: MCP Server for Claude / Stdio transport
Requires-Python: >=3.13
Requires-Dist: fastmcp>=2.13.0
Requires-Dist: httpx>=0.28.1
Requires-Dist: python-dotenv>=1.2.1
Requires-Dist: starlette>=0.50.0
